robot_keyframe_kit/__init__.py
robot_keyframe_kit/config.py
robot_keyframe_kit/editor.py
robot_keyframe_kit/keyframe.py
robot_keyframe_kit/math_utils.py
robot_keyframe_kit/sim_worker.py
robot_keyframe_kit-0.1.2.dist-info/licenses/LICENSE
robot_keyframe_kit-0.1.2.dist-info/METADATA
robot_keyframe_kit-0.1.2.dist-info/WHEEL
robot_keyframe_kit-0.1.2.dist-info/entry_points.txt
robot_keyframe_kit-0.1.2.dist-info/top_level.txt
robot_keyframe_kit-0.1.2.dist-info/RECORD
