Metadata-Version: 2.4
Name: robot-keyframe-kit
Version: 0.1.2
Summary: A generalizable Viser-based keyframe editor for any MuJoCo robot
Author-email: Stanford TML <yuming29@stanford.edu>
Maintainer-email: Stanford TML <yuming29@stanford.edu>
License-Expression: MIT
Project-URL: Homepage, https://github.com/Stanford-TML/robot_keyframe_kit
Project-URL: Repository, https://github.com/Stanford-TML/robot_keyframe_kit
Keywords: robotics,mujoco,keyframe,animation,viser,motion-planning
Classifier: Development Status :: 3 - Alpha
Classifier: Intended Audience :: Science/Research
Classifier: Intended Audience :: Developers
Classifier: Operating System :: OS Independent
Classifier: Programming Language :: Python :: 3
Classifier: Programming Language :: Python :: 3.9
Classifier: Programming Language :: Python :: 3.10
Classifier: Programming Language :: Python :: 3.11
Classifier: Programming Language :: Python :: 3.12
Classifier: Topic :: Scientific/Engineering
Classifier: Topic :: Scientific/Engineering :: Artificial Intelligence
Requires-Python: >=3.9
License-File: LICENSE
Requires-Dist: mujoco>=3.0
Requires-Dist: viser-keyframe==1.0.18
Requires-Dist: numpy
Requires-Dist: scipy
Requires-Dist: joblib
Requires-Dist: trimesh
Requires-Dist: lz4
Requires-Dist: pyyaml
Provides-Extra: dev
Requires-Dist: pytest; extra == "dev"
Requires-Dist: black; extra == "dev"
Requires-Dist: ruff; extra == "dev"
Dynamic: license-file
